LICENSE
MANIFEST.in
README.rst
setup.py
docs/changelog.rst
docs/conf.py
docs/customisation.rst
docs/faq.rst
docs/index.rst
docs/installation.rst
docs/overview.rst
docs/_build/html/_images/browse_table.png
docs/_build/html/_images/db_overview.png
docs/_build/html/_images/edit_table_data.png
docs/_build/html/_images/table_structure.png
docs/_build/html/_static/basic.css
docs/_build/html/_static/comment-bright.png
docs/_build/html/_static/comment-close.png
docs/_build/html/_static/comment.png
docs/_build/html/_static/contents.png
docs/_build/html/_static/down-pressed.png
docs/_build/html/_static/down.png
docs/_build/html/_static/file.png
docs/_build/html/_static/minus.png
docs/_build/html/_static/navigation.png
docs/_build/html/_static/plus.png
docs/_build/html/_static/pygments.css
docs/_build/html/_static/sphinxdoc.css
docs/_build/html/_static/up-pressed.png
docs/_build/html/_static/up.png
docs/_theme/vlinux/static/contents.png
docs/_theme/vlinux/static/navigation.png
docs/_theme/vlinux/static/sphinxdoc.css
docs/images/browse_table.png
docs/images/browse_table_2.png
docs/images/db_overview.png
docs/images/edit_table_data.png
docs/images/request_permission.png
docs/images/table_structure.png
tiote/__init__.py
tiote/models.py
tiote/urls.py
tiote.egg-info/PKG-INFO
tiote.egg-info/SOURCES.txt
tiote.egg-info/dependency_links.txt
tiote.egg-info/top_level.txt
tiote/forms/__init__.py
tiote/forms/common.py
tiote/forms/mysqlforms.py
tiote/forms/pgforms.py
tiote/sa/__init__.py
tiote/sql/__init__.py
tiote/sql/mysql.py
tiote/sql/pgsql.py
tiote/static/tt_css/bootstrap.css
tiote/static/tt_css/simplemodal.css
tiote/static/tt_css/spinner.css
tiote/static/tt_css/tiote.css
tiote/static/tt_img/database.png
tiote/static/tt_img/databases.png
tiote/static/tt_img/goback.png
tiote/static/tt_img/goto.png
tiote/static/tt_img/schema.png
tiote/static/tt_img/schemas.png
tiote/static/tt_img/sequence.png
tiote/static/tt_img/sequences.png
tiote/static/tt_img/sortasc.gif
tiote/static/tt_img/sortdesc.gif
tiote/static/tt_img/spinner.gif
tiote/static/tt_img/table.png
tiote/static/tt_img/tables.png
