Metadata-Version: 1.1
Name: tiote
Version: 0.2.4
Summary: Database administrator written in Python
Home-page: https://github.com/dumb906/tiote
Author: dumb906
Author-email: dumb906@gmail.com
License: UNKNOWN
Keywords: database,CRUD,data
Platform: UNKNOWN
Classifier: Programming Language :: Python
Classifier: Development Status :: 4 - Beta
Classifier: License :: OSI Approved :: MIT License
Classifier: Framework :: Django
Classifier: Operating System :: OS Independent
Classifier: Topic :: Database
Classifier: Topic :: Database :: Front-Ends
